[[{"location":"C:\\Users\\RCS\\Documents\\Java\\CS 311 Project 1","type":"PROJECT","hints":{"PROJECT_NAME":"CS 311 Project 1"}},"ABSENT"],[{"location":"C:\\Program Files\\Java\\jre1.8.0_31","type":"JRE","hints":{"EXECUTION_ENVIRONMENT":"JavaSE-1.8"}},"jre:jre:1.8.0"],[{"location":"C:\\Users\\RCS\\Documents\\Java\\301 Project 1 Bisection-Newton","type":"PROJECT","hints":{"PROJECT_NAME":"301 Project 1 Bisection-Newton"}},"ABSENT"],[{"location":"C:\\Users\\RCS\\Documents\\Java\\331 Project 2 Graphs - Prims Kruskle","type":"PROJECT","hints":{"PROJECT_NAME":"331 Project 2 Graphs - Prims Kruskle"}},"ABSENT"],[{"location":"C:\\Users\\RCS\\Documents\\Java\\TechTest","type":"PROJECT","hints":{"PROJECT_NAME":"TechTest"}},"ABSENT"],[{"location":"C:\\Program Files\\Java\\jre1.8.0_31","type":"JRE","hints":{}},"jre:jre:1.8.0"],[{"location":"C:\\Program Files (x86)\\Java\\jre7","type":"JRE","hints":{"EXECUTION_ENVIRONMENT":"JavaSE-1.7"}},"jre:jre:1.7.0"],[{"location":"C:\\Users\\RCS\\Documents\\Java\\331 Project 3 - A-Star vs Dijkstra\u0027s","type":"PROJECT","hints":{"PROJECT_NAME":"331 Project 3 - A-Star vs Dijkstra\u0027s"}},"ABSENT"]]